lagrange/__init__.py
lagrange/lagrange.py
lagrange-4.0.1.dist-info/licenses/LICENSE
lagrange-4.0.1.dist-info/METADATA
lagrange-4.0.1.dist-info/WHEEL
lagrange-4.0.1.dist-info/top_level.txt
lagrange-4.0.1.dist-info/RECORD
